[
  {
    "method": "GET",
    "path": "/images/:id",
    "name": "github.com/neoplatonist/pixr/server.(*fileHandler).getImage-fm"
  },
  {
    "method": "GET",
    "path": "/*",
    "name": "github.com/labstack/echo/v4.common.static.func1"
  },
  {
    "method": "GET",
    "path": "/upload",
    "name": "github.com/labstack/echo/v4.common.file.func1"
  },
  {
    "method": "POST",
    "path": "/images",
    "name": "github.com/neoplatonist/pixr/server.(*quotaLimiter).limit.func1"
  },
  {
    "method": "GET",
    "path": "/privacypolicy",
    "name": "github.com/labstack/echo/v4.common.file.func1"
  },
  {
    "method": "GET",
    "path": "/images",
    "name": "github.com/neoplatonist/pixr/server.(*fileHandler).getImages-fm"
  },
  {
    "method": "GET",
    "path": "/images/data/*",
    "name": "github.com/labstack/echo/v4.common.static.func1"
  },
  {
    "method": "GET",
    "path": "/about",
    "name": "github.com/labstack/echo/v4.common.file.func1"
  },
  {
    "method": "GET",
    "path": "/tos",
    "name": "github.com/labstack/echo/v4.common.file.func1"
  }
]